{"resourceType":"Bundle","id":"c4194509-c044-45f0-b0aa-4820d64d1bd7","meta":{"lastUpdated":"2018-04-18T10:40:41.378-04:00"},"type":"searchset","total":1,"link":[{"url":"https://sandbox.bluebutton.cms.gov/v1/fhir/Patient/?startIndex=0&count=10","relation":"self"}],"entry":[{"fullUrl":"https://sandbox.bluebutton.cms.gov/v1/fhir/Patient/20140000001920","resource":{"resourceType":"Patient","id":"20140000001920","extension":[{"url":"https://bluebutton.cms.gov/resources/variables/race","valueCoding":{"system":"https://bluebutton.cms.gov/resources/variables/race","code":"1","display":"White"}}],"identifier":[{"system":"https://bluebutton.cms.gov/resources/variables/bene_id","value":"20140000001920"},{"system":"https://bluebutton.cms.gov/resources/identifier/hicn-hash","value":"357e79ff0c9d5b559da18fea4fe647e6ad3ddf3a9515c0a2ffaad94072e0a53e"}],"name":[{"use":"usual","family":"Doe","given":["Jane","X"]}],"gender":"unknown","birthDate":"2014-06-01","address":[{"district":"999","state":"39","postalCode":"99999"}]}}]}